_curses.cp311-win_amd64.pyd
_curses_panel.cp311-win_amd64.pyd
windows_curses_ywmod-2.3.2a3.dist-info/LICENSE
windows_curses_ywmod-2.3.2a3.dist-info/METADATA
windows_curses_ywmod-2.3.2a3.dist-info/WHEEL
windows_curses_ywmod-2.3.2a3.dist-info/top_level.txt
windows_curses_ywmod-2.3.2a3.dist-info/RECORD
