Metadata-Version: 2.1
Name: windows-curses-ywmod
Version: 2.3.2a3
Summary: Support for the standard curses module on Windows
Home-page: https://github.com/YWtheGod/windows-curses
License: PSF2
Project-URL: GitHub repository, https://github.com/YWtheGod/windows-curses
Classifier: Development Status :: 4 - Beta
Classifier: Environment :: Console :: Curses
Classifier: Environment :: Win32 (MS Windows)
Classifier: License :: OSI Approved :: Python Software Foundation License
Classifier: Operating System :: Microsoft :: Windows
Classifier: Programming Language :: C
Classifier: Programming Language :: Python
Classifier: Programming Language :: Python :: 3.6
Classifier: Programming Language :: Python :: 3.7
Classifier: Programming Language :: Python :: 3.8
Classifier: Programming Language :: Python :: 3.9
Classifier: Programming Language :: Python :: 3.10
Classifier: Programming Language :: Python :: 3.11
Classifier: Programming Language :: Python :: 3.12
Classifier: Programming Language :: Python :: Implementation :: CPython
Classifier: Topic :: Software Development
Classifier: Topic :: Software Development :: Libraries :: Python Modules
License-File: LICENSE
